werkdone_excel_server/__init__.py
werkdone_excel_server/server.py
werkdone_excel_server/tools/ExcelTools.py
werkdone_excel_server/tools/cell_utils.py
werkdone_excel_server/tools/cell_validation.py
werkdone_excel_server/tools/data.py
werkdone_excel_server/tools/exceptions.py
werkdone_excel_server/tools/workbook.py
werkdone_excel_server-1.1.12.dist-info/METADATA
werkdone_excel_server-1.1.12.dist-info/WHEEL
werkdone_excel_server-1.1.12.dist-info/entry_points.txt
werkdone_excel_server-1.1.12.dist-info/top_level.txt
werkdone_excel_server-1.1.12.dist-info/RECORD
