Metadata-Version: 2.4
Name: werkdone-excel-server
Version: 1.1.12
Summary: MCP Excel Tool Server for generating visitation reports
Author-email: Obie Ananda <Obie.kal22@gmail.com>
Requires-Python: >=3.11
Requires-Dist: mcp[cli]>=1.10.1
Requires-Dist: openpyxl>=3.1.5
Requires-Dist: smolagents[mcp]>=1.19.0
Requires-Dist: twine>=6.1.0
